modules/exp_adjust.v
/*
* The module adjusts the resultin exponent of the resulting number.
* The constant shift by 2 term is the result of left extending the mantisa 
* register to accomodate for implicit 1 and possible addition overflow
*/

module exp_adjust(e,sh,e_out);
    input  [7:0] e;
    input  [4:0] sh;

    output [7:0] e_out;

    assign e_out = e + 2'b10 - sh;
endmodule

modules/sh_logic_left.v
/*
* This module performs shifting left of the mantisa by given amount
* It also reduce the width of resulting vector from the extended
* size used in mantisa addition to IEEE size. Both sizes
* are parametrized to allow flexibility
*/

module sh_logic_left(m, sh, out);
    parameter WIDTH = 1;
    parameter WIDTH_OUT = 1;

    input [WIDTH-1:0]       m;
    input [4:0]            sh;

    output[WIDTH_OUT-1:0] out;

    wire   [WIDTH-1:0] m_d;

    assign m_d = m << sh;
    assign out = m_d[WIDTH-1:WIDTH-WIDTH_OUT];
endmodule

modules/detector_shift.v
/*
* Module is used in normalization of mantisa
* It detects the amount of shif required to bring
* the mantisa int 1.xxx form
*
* The two outputs are:
*  sh - is the amount of shift that has to be done on mantisa
*  exp_adj - is the adjustment of the resulting exponent
*
* The module handles special case when the result is zero, the module
* Makes adjustments necesarry for nest stage exponent adjustment component
* to correctly calculate resulting exponent of 0.
* 
* In general case the sh and exp_adj hold the same value
*/
module detector_shift(m, sh, exp_adj);
    parameter WIDTH = 1;

    input  [WIDTH-1:0] m;
    output [4:0]       sh;
    output [4:0]       exp_adj;

    //Internal connections
    reg    [4:0]       sh_d;
    reg    [4:0]       exp_adj_d;
    reg                done; 
    integer            i;

    always @(*) begin
        if( | m == 1'b0 ) begin // Zero case
            sh_d = 0;
            exp_adj_d = 2'b10; //add correction for next stage
        end else begin // Non zero case
            done = 1'b0;
            i=WIDTH-1;
            sh_d = 0;

            //iterate over array until bit value 1 is encountered
            while(done == 1'b0) begin
                sh_d = sh_d+1;
                if(m[i] == 1'b1 || i == 0) 
                    done = 1'b1;
                i = i-1;
            end
            exp_adj_d = sh;
        end
    end

    assign sh = sh_d;
    assign exp_adj = exp_adj_d;
endmodule

modules/adder.v
/*
* Module adding two integer numbers
*/

module adder(a, b, sum);
    parameter WIDTH = 1;

    input  [WIDTH-1:0] a;
    input  [WIDTH-1:0] b;

    output [WIDTH-1:0] sum;

    assign sum = a+b;
endmodule

modules/selector_sign.v
/* This module makes the selection of which value(A or B)
* sign should be propagated further in the following way:
* 
* if signs different then
*   if mantisaA < mantisa B then
*       propagate sign_bit_B
*   otherwise
*       propagate sign_bit_A
*   endif
* otherwise
*   propagate sign_bit_A
* endif
*
*/

module sign_selector(sa, sb, a_lt_b, s);
    input   sa;
    input   sb;
    input   a_lt_b;

    output  s;

    //internal connections
    reg s_d;

    always @(*) begin
        if( (sa ^ sb) == 1'b1) begin
            if(a_lt_b == 1'b1)
                s_d = sb;
            else
                s_d = sa;
        end else begin
            s_d = sa;
        end
    end

    assign s = s_d;
endmodule

modules/mux2.v
/*
* Two input mutex
*/

module mux2(i0, i1, o, s);
    parameter WIDTH = 1;

    input  [WIDTH-1:0] i0;
    input  [WIDTH-1:0] i1;
    input              s;

    output [WIDTH-1:0] o;

    assign o = (s == 1'b0) ? i0 : i1;
endmodule

modules/compl2.v
/*
* Module calculating 2's complement of a given number
*/

module compl2 (i, o);
    parameter WIDTH = 1;

    input  [WIDTH-1:0] i;

    output [WIDTH-1:0] o;

    assign o = ~i + 1'b1;
endmodule

modules/lt_comp.v
/*
* This module detects the condition
* mantisa_A < mantisa_B
*/
module lt_comp(a, b, o);
    parameter WIDTH = 1;

    input [WIDTH-1:0] a;
    input [WIDTH-1:0] b;

    output            o;

    assign o = a < b;
endmodule

modules/sh_logic_right.v
/* 
* This module performs right shift by given amount
* when enable bit is high
*/

module sh_logic_right(d, shamt, en, out);
    input [24:0] d;
    input  [4:0] shamt;
    input        en;
    
    output [24:0] out;

    assign out = (en == 1'b1) ? d >> shamt : d;

endmodule

modules/exp_comp.v
/*
* This module detects the difference in exponents of two given number. 
* At its output it sends information about which number was smaller
* and how many spaces should its mantisa be shifted right.
* There is an upper bound of 24 places at which the number become
* insignificant and it si treated as zero.
*
* In the case when two numbers have the same exponent the signal to shift
* is by default made for number A with the right shift of 0.
*/
module exp_comp(e_a, e_b, shamt, sh_ab);

    input [7:0] e_a;
    input [7:0] e_b;

    output [4:0] shamt;
    output sh_ab;


    //internal connections
    reg [4:0] conn_shamt;
    reg conn_sh_ab;


    always @(*) begin
        if(e_a <= e_b) begin
            //reduce shift if over maximum 24
            if(e_b - e_a > 24)
                conn_shamt = 24;
            else
                conn_shamt = e_b - e_a;
            //shift A
            conn_sh_ab = 1'b0;
        end else begin
            //reduce shift if over maximum 24
            if(e_a - e_b > 24) 
                conn_shamt = 24;
            else
                conn_shamt = e_a - e_b;

            //shift B
            conn_sh_ab = 1'b1;
        end
    end

    assign shamt = conn_shamt;
    assign sh_ab = conn_sh_ab;
endmodule

fp_adder_single_cycle.v
`include "modules/exp_comp.v"
`include "modules/sh_logic_right.v"
`include "modules/mux2.v"
`include "modules/lt_comp.v"
`include "modules/compl2.v"
`include "modules/selector_sign.v"
`include "modules/adder.v"
`include "modules/detector_shift.v"
`include "modules/sh_logic_left.v"
`include "modules/exp_adjust.v"

/*
* Main floating point adder module single cycle
*/

module fp_adder_single_cycle(a, b, sum);
    input [31:0] a;
    input [31:0] b;

    output [31:0] sum;

    wire [4:0] U1_shamt;
    wire       U1_sh_ab;

    //detect which numbers mantisa to shift ans by how much
    exp_comp U1(.e_a(a[30:23]),
                .e_b(b[30:23]),
                .shamt(U1_shamt),
                .sh_ab(U1_sh_ab)
                );



    wire [24:0] U2_o;
    
    //Shift mantisa of number A to the right if enabled
    sh_logic_right U2(.d({2'b01,a[22:0]}),
                      .shamt(U1_shamt),
                      .en(~U1_sh_ab),
                      .out(U2_o)
                      );

    wire [24:0] U3_o;
    
    //Shift mantisa of number B to the right if enabled
    sh_logic_right U3(.d({2'b01,b[22:0]}),
                      .shamt(U1_shamt),
                      .en(U1_sh_ab),
                      .out(U3_o)
                      );


    wire [7:0] U4_e;

    //Select larger exponent to propagate
    mux2 #(.WIDTH(8)) U4(.i0(a[30:23]),
                         .i1(b[30:23]),
                         .o(U4_e),
                         .s(~U1_sh_ab)
                         );

    wire        sa;
    wire        sb;

    //Propagate sign bits
    assign sa = a[31];
    assign sb = b[31];

    //Hardwired extended zero mantisa
    wire [24:0] m_exp_zero;
    assign m_exp_zero = 25'b0;

    //Detecting the zero number for first argument
    //If detected propoagate 0 mantisa instead of 01.xxx mantisa
    wire ma_zero_cond;
    assign ma_zero_cond = (a[30:0] == 30'b0) ? 1'b1 : 1'b0;
    wire [24:0] U5_ma;
    mux2 #(.WIDTH(25)) U5(.i0(U2_o),
                          .i1(m_exp_zero),
                          .o(U5_ma),
                          .s(ma_zero_cond)
                         );

    //Detecting the zero number for second arguent
    //If detected propoagate 0 mantisa instead of 01.xxx mantisa
    wire mb_zero_cond;
    assign mb_zero_cond = (b[30:0] == 30'b0) ? 1'b1 : 1'b0;
    wire [24:0] U6_mb;
    mux2 #(.WIDTH(25)) U6(.i0(U3_o),
                          .i1(m_exp_zero),
                          .o(U6_mb),
                          .s(mb_zero_cond)
                         );

    //Testing which mantisa is smaller
    wire U7_a_lt_b;
    lt_comp #(.WIDTH(25)) U7(.a(U5_ma),
                             .b(U6_mb),
                             .o(U7_a_lt_b)
                            );
                            
    wire signs_diff;

    //Testing if signs are different
    assign signs_diff = sa ^ sb;
    
    wire [24:0] U8_ma_compl2;

    //precomputing the 2's complement of mantisa A
    compl2 #(.WIDTH(25)) U8(.i(U5_ma),
                            .o(U8_ma_compl2)
                        );

    wire [24:0] U9_mb_compl2;

    //precomputing the 2's complement of mantisa B
    compl2 #(.WIDTH(25)) U9(.i(U6_mb),
                            .o(U9_mb_compl2)
                        );

    wire sel_ma_compl;
    assign sel_ma_compl = (signs_diff==1'b1 && U7_a_lt_b==1'b1) ? 1'b1 : 1'b0;

    wire [24:0] U10_m1;
    
    //Propagate 2's complement of mantisa A if mantisa_A < mantisa B and signs
    //are different
    mux2 #(.WIDTH(25)) U10(.i0(U5_ma),
                           .i1(U8_ma_compl2),
                           .o(U10_m1),
                           .s(sel_ma_compl)
                       );

    wire sel_mb_compl;
    assign sel_mb_compl = (signs_diff==1'b1 && U7_a_lt_b==1'b0) ? 1'b1 : 1'b0;

    wire [24:0] U11_m2;

    //Propagate 2's complement of mantisa B if mantisa_B < mantisa_A and signs
    //are different
    mux2 #(.WIDTH(25)) U11(.i0(U6_mb),
                           .i1(U9_mb_compl2),
                           .o(U11_m2),
                           .s(sel_mb_compl)
                       );

    wire U12_s;

    //Select sign bit of A or B to propagate
    sign_selector U12(.sa(sa),
                      .sb(sb),
                      .a_lt_b(U7_a_lt_b),
                      .s(U12_s)
                  );

    //Add mantisas
    wire [24:0] U13_m;
    adder #(.WIDTH(25)) U13(.a(U10_m1),
                            .b(U11_m2),
                            .sum(U13_m)
                        );

    wire [4:0] U14_sh;
    wire [4:0] U14_exp_adj;
    
    //Determine the amount of shift for normalization
    detector_shift #(.WIDTH(25)) U14(.m(U13_m),
                                    .sh(U14_sh),
                                    .exp_adj(U14_exp_adj)
                                );

    wire [22:0] U15_m_out;

    //Normalize mantisa
    sh_logic_left #(.WIDTH(25), .WIDTH_OUT(23)) U15(.m(U13_m),
                                                    .sh(U14_sh),
                                                    .out(U15_m_out)
                                                );

    //Adjust exponent
    wire [7:0] U16_e_out;
    exp_adjust U16(.e(U4_e),
                   .sh(U14_exp_adj),
                   .e_out(U16_e_out)
               );

    //Combine result
    assign sum = {U12_s, U16_e_out, U15_m_out};

endmodule

top_single_cycle.v
`timescale 1ns/10ps

`include "fp_adder_single_cycle.v"

/*
* Top module test bench of single cycle floating point adder
*/
module top();
    reg [31:0] test_A [0:7];
    reg [31:0] test_B [0:7];
    reg [31:0] test_SUM [0:7];
    
    integer test_num_cases;

    //Populate set with test vectors
    task populate_test_set;
    begin
        test_A[0] =   32'b0_10000101_10001000000000000000000; //98
        test_B[0] =   32'b0_10000110_01010010000000000000000; //169
        test_SUM[0] = 32'b0_10000111_00001011000000000000000; //267 

        test_A[1] =   32'b0_10000101_10001100000000000000000; //99
        test_B[1] =   32'b1_10000101_01100100000000000000000; //-89
        test_SUM[1] = 32'b0_10000010_01000000000000000000000; //10
        
        test_A[2] =   32'b1_10000100_01101000000000000000000; //-45
        test_B[2] =   32'b0_10000101_00111100000000000000000; //79
        test_SUM[2] = 32'b0_10000100_00010000000000000000000; //34

        test_A[3] =   32'b1_10000111_00011011000000000000000; //-283
        test_B[3] =   32'b1_10000101_00001000000000000000000; //-66
        test_SUM[3] = 32'b1_10000111_01011101000000000000000; //-349

        test_A[4] =   32'b0_00000000_00000000000000000000000; //0
        test_B[4] =   32'b0_00000000_00000000000000000000000; //0
        test_SUM[4] = 32'b0_00000000_00000000000000000000000; //0

        test_A[5] =   32'b0_00000000_00000000000000000000000; //0
        test_B[5] =   32'b1_10000101_11010100000000000000000; //-117
        test_SUM[5] = 32'b1_10000101_11010100000000000000000;

        test_A[6] =   32'b1_10000101_10111000100000000000000; //-110.125
        test_B[6] =   32'b0_10000101_10001111100000000000000; //99.875
        test_SUM[6] = 32'b1_10000010_01001000000000000000000; //-10.25

        test_A[7] =   32'b0_10000101_10111011100000000000000; //110.875
        test_B[7] =   32'b0_10000101_10001100100000000000000; //99.125
        test_SUM[7] = 32'b0_10000110_10100100000000000000000; //210

        test_num_cases = 8;
    end
    endtask


    //Instantiate device under test
    reg  [31:0] FP_ADD_SC_I_A;
    reg  [31:0] FP_ADD_SC_I_B;
    wire [31:0] FP_ADD_SC_O_SUM;
    fp_adder_single_cycle FP_ADD_SC_DUT(.a(FP_ADD_SC_I_A),
                                        .b(FP_ADD_SC_I_B),
                                        .sum(FP_ADD_SC_O_SUM)
                                        );


    //Testing procedure
    //For single entry in test vector set the inputs and compare
    //the output with expected value
    task test_1cycle;
        integer i;
    begin
        $display("Testing single cycle floating point adder");
        for(i=0; i< test_num_cases; i=i+1) begin
            FP_ADD_SC_I_A = test_A[i];
            FP_ADD_SC_I_B = test_B[i];

            #1;
            $display("-------------------------");
            $display("Test case: %d", i);
            $display("A:       %b", FP_ADD_SC_I_A);
            $display("B:       %b", FP_ADD_SC_I_B);
            $display("SUM:     %b", FP_ADD_SC_O_SUM);
            $display("EXP SUM: %b", test_SUM[i]);

            if(FP_ADD_SC_O_SUM == test_SUM[i]) begin
                $display("PASSED");
            end else begin
                $display("FAILED");
            end

        end
    end
    endtask

    initial begin : TEST_MAIN
        //Dump variables for timing diagrams
        $dumpfile("test_single_cycle.vcd");
        $dumpvars;

        populate_test_set();
        test_1cycle();
        
        $finish();
    end
endmodule

test_single_cycle.vcd
$date
	Sun May 12 22:24:45 2019
$end
$version
	Icarus Verilog
$end
$timescale
	10ps
$end
$scope module top $end
$var wire 32 ! FP_ADD_SC_O_SUM [31:0] $end
$var reg 32 " FP_ADD_SC_I_A [31:0] $end
$var reg 32 # FP_ADD_SC_I_B [31:0] $end
$var integer 32 $ test_num_cases [31:0] $end
$scope module FP_ADD_SC_DUT $end
$var wire 32 % a [31:0] $end
$var wire 32 & b [31:0] $end
$var wire 25 ' m_exp_zero [24:0] $end
$var wire 1 ( signs_diff $end
$var wire 32 ) sum [31:0] $end
$var wire 1 * sel_mb_compl $end
$var wire 1 + sel_ma_compl $end
$var wire 1 , sb $end
$var wire 1 - sa $end
$var wire 1 . mb_zero_cond $end
$var wire 1 / ma_zero_cond $end
$var wire 25 0 U9_mb_compl2 [24:0] $end
$var wire 25 1 U8_ma_compl2 [24:0] $end
$var wire 1 2 U7_a_lt_b $end
$var wire 25 3 U6_mb [24:0] $end
$var wire 25 4 U5_ma [24:0] $end
$var wire 8 5 U4_e [7:0] $end
$var wire 25 6 U3_o [24:0] $end
$var wire 25 7 U2_o [24:0] $end
$var wire 5 8 U1_shamt [4:0] $end
$var wire 1 9 U1_sh_ab $end
$var wire 8 : U16_e_out [7:0] $end
$var wire 23 ; U15_m_out [22:0] $end
$var wire 5 < U14_sh [4:0] $end
$var wire 5 = U14_exp_adj [4:0] $end
$var wire 25 > U13_m [24:0] $end
$var wire 1 ? U12_s $end
$var wire 25 @ U11_m2 [24:0] $end
$var wire 25 A U10_m1 [24:0] $end
$scope module U1 $end
$var wire 8 B e_a [7:0] $end
$var wire 8 C e_b [7:0] $end
$var wire 1 9 sh_ab $end
$var wire 5 D shamt [4:0] $end
$var reg 1 9 conn_sh_ab $end
$var reg 5 E conn_shamt [4:0] $end
$upscope $end
$scope module U10 $end
$var wire 1 + s $end
$var wire 25 F o [24:0] $end
$var wire 25 G i1 [24:0] $end
$var wire 25 H i0 [24:0] $end
$upscope $end
$scope module U11 $end
$var wire 1 * s $end
$var wire 25 I o [24:0] $end
$var wire 25 J i1 [24:0] $end
$var wire 25 K i0 [24:0] $end
$upscope $end
$scope module U12 $end
$var wire 1 - sa $end
$var wire 1 , sb $end
$var wire 1 ? s $end
$var wire 1 2 a_lt_b $end
$var reg 1 ? s_d $end
$upscope $end
$scope module U13 $end
$var wire 25 L a [24:0] $end
$var wire 25 M b [24:0] $end
$var wire 25 N sum [24:0] $end
$upscope $end
$scope module U14 $end
$var wire 25 O m [24:0] $end
$var wire 5 P sh [4:0] $end
$var wire 5 Q exp_adj [4:0] $end
$var reg 1 R done $end
$var reg 5 S exp_adj_d [4:0] $end
$var reg 5 T sh_d [4:0] $end
$var integer 32 U i [31:0] $end
$upscope $end
$scope module U15 $end
$var wire 25 V m [24:0] $end
$var wire 5 W sh [4:0] $end
$var wire 23 X out [22:0] $end
$var wire 25 Y m_d [24:0] $end
$upscope $end
$scope module U16 $end
$var wire 5 Z sh [4:0] $end
$var wire 8 [ e_out [7:0] $end
$var wire 8 \ e [7:0] $end
$upscope $end
$scope module U2 $end
$var wire 25 ] d [24:0] $end
$var wire 1 ^ en $end
$var wire 5 _ shamt [4:0] $end
$var wire 25 ` out [24:0] $end
$upscope $end
$scope module U3 $end
$var wire 25 a d [24:0] $end
$var wire 1 9 en $end
$var wire 5 b shamt [4:0] $end
$var wire 25 c out [24:0] $end
$upscope $end
$scope module U4 $end
$var wire 8 d i0 [7:0] $end
$var wire 8 e i1 [7:0] $end
$var wire 1 f s $end
$var wire 8 g o [7:0] $end
$upscope $end
$scope module U5 $end
$var wire 25 h i0 [24:0] $end
$var wire 25 i i1 [24:0] $end
$var wire 1 / s $end
$var wire 25 j o [24:0] $end
$upscope $end
$scope module U6 $end
$var wire 25 k i0 [24:0] $end
$var wire 25 l i1 [24:0] $end
$var wire 1 . s $end
$var wire 25 m o [24:0] $end
$upscope $end
$scope module U7 $end
$var wire 25 n a [24:0] $end
$var wire 25 o b [24:0] $end
$var wire 1 2 o $end
$upscope $end
$scope module U8 $end
$var wire 25 p i [24:0] $end
$var wire 25 q o [24:0] $end
$upscope $end
$scope module U9 $end
$var wire 25 r i [24:0] $end
$var wire 25 s o [24:0] $end
$upscope $end
$upscope $end
$scope begin TEST_MAIN $end
$upscope $end
$scope task populate_test_set $end
$upscope $end
$scope task test_1cycle $end
$var integer 32 t i [31:0] $end
$upscope $end
$upscope $end
$enddefinitions $end
#0
$dumpvars
b0 t
b1010101110000000000000000 s
b101010010000000000000000 r
b1100111100000000000000000 q
b11000100000000000000000 p
b101010010000000000000000 o
b11000100000000000000000 n
b101010010000000000000000 m
b0 l
b101010010000000000000000 k
b11000100000000000000000 j
b0 i
b11000100000000000000000 h
b10000110 g
1f
b10000110 e
b10000101 d
b101010010000000000000000 c
b1 b
b101010010000000000000000 a
b11000100000000000000000 `
b1 _
1^
b110001000000000000000000 ]
b10000110 \
b10000111 [
b1 Z
b101100000000000000000 Y
b1011000000000000000 X
b1 W
b1000010110000000000000000 V
b10111 U
b1 T
b1 S
1R
b1 Q
b1 P
b1000010110000000000000000 O
b1000010110000000000000000 N
b101010010000000000000000 M
b11000100000000000000000 L
b101010010000000000000000 K
b1010101110000000000000000 J
b101010010000000000000000 I
b11000100000000000000000 H
b1100111100000000000000000 G
b11000100000000000000000 F
b1 E
b1 D
b10000110 C
b10000101 B
b11000100000000000000000 A
b101010010000000000000000 @
0?
b1000010110000000000000000 >
b1 =
b1 <
b1011000000000000000 ;
b10000111 :
09
b1 8
b11000100000000000000000 7
b101010010000000000000000 6
b10000110 5
b11000100000000000000000 4
b101010010000000000000000 3
12
b1100111100000000000000000 1
b1010101110000000000000000 0
0/
0.
0-
0,
0+
0*
b1000011100001011000000000000000 )
0(
b0 '
b1000011001010010000000000000000 &
b1000010110001000000000000000000 %
b1000 $
b1000011001010010000000000000000 #
b1000010110001000000000000000000 "
b1000011100001011000000000000000 !
$end
#100
b101 =
b101 Q
b101 S
b101 Z
1*
0+
b1000000000000000000000 ;
b1000000000000000000000 X
b101 <
b101 P
b101 T
b101 W
b10011 U
1R
02
b1010011100000000000000000 0
b1010011100000000000000000 J
b1010011100000000000000000 s
b1010011100000000000000000 @
b1010011100000000000000000 I
b1010011100000000000000000 M
b1001110100000000000000000 1
b1001110100000000000000000 G
b1001110100000000000000000 q
b100000000000000000000000 Y
b101000000000000000000 >
b101000000000000000000 N
b101000000000000000000 O
b101000000000000000000 V
b110001100000000000000000 A
b110001100000000000000000 F
b110001100000000000000000 L
b101100100000000000000000 3
b101100100000000000000000 K
b101100100000000000000000 m
b101100100000000000000000 o
b101100100000000000000000 r
b110001100000000000000000 4
b110001100000000000000000 H
b110001100000000000000000 j
b110001100000000000000000 n
b110001100000000000000000 p
b0 8
b0 D
b0 E
b0 _
b0 b
b101100100000000000000000 6
b101100100000000000000000 c
b101100100000000000000000 k
b10000010 :
b10000010 [
b10000101 5
b10000101 \
b10000101 g
b1000001001000000000000000000000 !
b1000001001000000000000000000000 )
0?
1(
b110001100000000000000000 7
b110001100000000000000000 `
b110001100000000000000000 h
b10000101 C
b101100100000000000000000 a
b10000101 e
1,
b110001100000000000000000 ]
b11000010101100100000000000000000 #
b11000010101100100000000000000000 &
b1000010110001100000000000000000 "
b1000010110001100000000000000000 %
b1 t
#200
0*
1+
b100111100000000000000000 @
b100111100000000000000000 I
b100111100000000000000000 M
b10000000000000000000 ;
b10000000000000000000 X
b10000100 :
b10000100 [
b11 =
b11 Q
b11 S
b11 Z
b11 <
b11 P
b11 T
b11 W
b10101 U
1R
b1011000100000000000000000 0
b1011000100000000000000000 J
b1011000100000000000000000 s
12
b1101001100000000000000000 1
b1101001100000000000000000 G
b1101001100000000000000000 q
b1000000000000000000000 Y
b10001000000000000000000 >
b10001000000000000000000 N
b10001000000000000000000 O
b10001000000000000000000 V
b1101001100000000000000000 A
b1101001100000000000000000 F
b1101001100000000000000000 L
b100111100000000000000000 3
b100111100000000000000000 K
b100111100000000000000000 m
b100111100000000000000000 o
b100111100000000000000000 r
b10110100000000000000000 4
b10110100000000000000000 H
b10110100000000000000000 j
b10110100000000000000000 n
b10110100000000000000000 p
b100111100000000000000000 6
b100111100000000000000000 c
b100111100000000000000000 k
b1 8
b1 D
b1 E
b1 _
b1 b
b10110100000000000000000 7
b10110100000000000000000 `
b10110100000000000000000 h
b1000010000010000000000000000000 !
b1000010000010000000000000000000 )
0?
b100111100000000000000000 a
0,
b10000100 B
b101101000000000000000000 ]
b10000100 d
1-
b1000010100111100000000000000000 #
b1000010100111100000000000000000 &
b11000010001101000000000000000000 "
b11000010001101000000000000000000 %
b10 t
#300
b1011101000000000000000 ;
b1011101000000000000000 X
b10 =
b10 Q
b10 S
b10 Z
b10 <
b10 P
b10 T
b10 W
b10110 U
1R
0+
02
b10000111 :
b10000111 [
b10000111 5
b10000111 \
b10000111 g
b100011011000000000000000 A
b100011011000000000000000 F
b100011011000000000000000 L
b1110111110000000000000000 0
b1110111110000000000000000 J
b1110111110000000000000000 s
b101110100000000000000000 Y
b101011101000000000000000 >
b101011101000000000000000 N
b101011101000000000000000 O
b101011101000000000000000 V
b1000010000000000000000 @
b1000010000000000000000 I
b1000010000000000000000 M
b1011100101000000000000000 1
b1011100101000000000000000 G
b1011100101000000000000000 q
b1000010000000000000000 3
b1000010000000000000000 K
b1000010000000000000000 m
b1000010000000000000000 o
b1000010000000000000000 r
0f
0^
b100011011000000000000000 4
b100011011000000000000000 H
b100011011000000000000000 j
b100011011000000000000000 n
b100011011000000000000000 p
b1000010000000000000000 6
b1000010000000000000000 c
b1000010000000000000000 k
b11000011101011101000000000000000 !
b11000011101011101000000000000000 )
1?
0(
19
b10 8
b10 D
b10 E
b10 _
b10 b
b100011011000000000000000 7
b100011011000000000000000 `
b100011011000000000000000 h
b100001000000000000000000 a
1,
b10000111 B
b100011011000000000000000 ]
b10000111 d
b11000010100001000000000000000000 #
b11000010100001000000000000000000 &
b11000011100011011000000000000000 "
b11000011100011011000000000000000 %
b11 t
#400
b0 ;
b0 X
b0 <
b0 P
b0 T
b0 W
b0 0
b0 J
b0 s
b0 @
b0 I
b0 M
b0 1
b0 G
b0 q
b0 Y
b0 >
b0 N
b0 O
b0 V
b0 A
b0 F
b0 L
b0 3
b0 K
b0 m
b0 o
b0 r
1f
1^
02
b0 4
b0 H
b0 j
b0 n
b0 p
b100000000000000000000000 6
b100000000000000000000000 c
b100000000000000000000000 k
1.
09
b0 8
b0 D
b0 E
b0 _
b0 b
b100000000000000000000000 7
b100000000000000000000000 `
b100000000000000000000000 h
b0 :
b0 [
b0 5
b0 \
b0 g
b0 !
b0 )
0?
1/
b0 C
b100000000000000000000000 a
b0 e
0,
b0 B
b100000000000000000000000 ]
b0 d
0-
b0 #
b0 &
b0 "
b0 %
b100 t
#500
b10 =
b10 Q
b10 S
b10 Z
1+
b11010100000000000000000 ;
b11010100000000000000000 X
b10 <
b10 P
b10 T
b10 W
b10110 U
1R
0*
1?
b1000101100000000000000000 0
b1000101100000000000000000 J
b1000101100000000000000000 s
b1101010000000000000000000 Y
b111010100000000000000000 >
b111010100000000000000000 N
b111010100000000000000000 O
b111010100000000000000000 V
b111010100000000000000000 @
b111010100000000000000000 I
b111010100000000000000000 M
12
b111010100000000000000000 3
b111010100000000000000000 K
b111010100000000000000000 m
b111010100000000000000000 o
b111010100000000000000000 r
b0 7
b0 `
b0 h
b11000 8
b11000 D
b11000 E
b11000 _
b11000 b
b111010100000000000000000 6
b111010100000000000000000 c
b111010100000000000000000 k
b11000010111010100000000000000000 !
b11000010111010100000000000000000 )
b10000101 :
b10000101 [
b10000101 5
b10000101 \
b10000101 g
1(
0.
b10000101 C
b111010100000000000000000 a
b10000101 e
1,
b11000010111010100000000000000000 #
b11000010111010100000000000000000 &
b101 t
#600
1*
0+
b10000010 :
b10000010 [
b101 =
b101 Q
b101 S
b101 Z
b110111000100000000000000 A
b110111000100000000000000 F
b110111000100000000000000 L
b1001000000000000000000 ;
b1001000000000000000000 X
b101 <
b101 P
b101 T
b101 W
b10011 U
1R
b1001000111100000000000000 1
b1001000111100000000000000 G
b1001000111100000000000000 q
b1001110000100000000000000 0
b1001110000100000000000000 J
b1001110000100000000000000 s
b100100000000000000000000 Y
b101001000000000000000 >
b101001000000000000000 N
b101001000000000000000 O
b101001000000000000000 V
b1001110000100000000000000 @
b1001110000100000000000000 I
b1001110000100000000000000 M
02
b110111000100000000000000 4
b110111000100000000000000 H
b110111000100000000000000 j
b110111000100000000000000 n
b110111000100000000000000 p
b110001111100000000000000 3
b110001111100000000000000 K
b110001111100000000000000 m
b110001111100000000000000 o
b110001111100000000000000 r
b110111000100000000000000 7
b110111000100000000000000 `
b110111000100000000000000 h
b110001111100000000000000 6
b110001111100000000000000 c
b110001111100000000000000 k
b0 8
b0 D
b0 E
b0 _
b0 b
b11000001001001000000000000000000 !
b11000001001001000000000000000000 )
1?
0/
b110001111100000000000000 a
0,
b10000101 B
b110111000100000000000000 ]
b10000101 d
1-
b1000010110001111100000000000000 #
b1000010110001111100000000000000 &
b11000010110111000100000000000000 "
b11000010110111000100000000000000 %
b110 t
#700
b10000110 :
b10000110 [
b1 =
b1 Q
b1 S
b1 Z
b110001100100000000000000 @
b110001100100000000000000 I
b110001100100000000000000 M
b10100100000000000000000 ;
b10100100000000000000000 X
b1 <
b1 P
b1 T
b1 W
b10111 U
1R
0*
b1001110011100000000000000 0
b1001110011100000000000000 J
b1001110011100000000000000 s
b1001000100100000000000000 1
b1001000100100000000000000 G
b1001000100100000000000000 q
b1010010000000000000000000 Y
b1101001000000000000000000 >
b1101001000000000000000000 N
b1101001000000000000000000 O
b1101001000000000000000000 V
b110111011100000000000000 A
b110111011100000000000000 F
b110111011100000000000000 L
b110001100100000000000000 3
b110001100100000000000000 K
b110001100100000000000000 m
b110001100100000000000000 o
b110001100100000000000000 r
b110111011100000000000000 4
b110111011100000000000000 H
b110111011100000000000000 j
b110111011100000000000000 n
b110111011100000000000000 p
b110001100100000000000000 6
b110001100100000000000000 c
b110001100100000000000000 k
b110111011100000000000000 7
b110111011100000000000000 `
b110111011100000000000000 h
b1000011010100100000000000000000 !
b1000011010100100000000000000000 )
0?
0(
b110001100100000000000000 a
b110111011100000000000000 ]
0-
b1000010110001100100000000000000 #
b1000010110001100100000000000000 &
b1000010110111011100000000000000 "
b1000010110111011100000000000000 %
b111 t
#800
b1000 t
